adafruit_slideshow.py
adafruit_circuitpython_slideshow-1.8.7.dist-info/licenses/LICENSE
adafruit_circuitpython_slideshow-1.8.7.dist-info/METADATA
adafruit_circuitpython_slideshow-1.8.7.dist-info/WHEEL
adafruit_circuitpython_slideshow-1.8.7.dist-info/top_level.txt
adafruit_circuitpython_slideshow-1.8.7.dist-info/RECORD
