Metadata-Version: 2.4
Name: adafruit-circuitpython-slideshow
Version: 1.8.7
Summary: CircuitPython helper library for displaying a slideshow of images on a display.
Author-email: Adafruit Industries <circuitpython@adafruit.com>
License: MIT
Project-URL: Homepage, https://github.com/adafruit/Adafruit_CircuitPython_Slideshow
Keywords: adafruit,software,slideshow,image,display,micropython,circuitpython
Classifier: Intended Audience :: Developers
Classifier: Topic :: Software Development :: Libraries
Classifier: Topic :: Software Development :: Embedded Systems
Classifier: Topic :: System :: Hardware
Classifier: License :: OSI Approved :: MIT License
Classifier: Programming Language :: Python :: 3
License-File: LICENSE
Requires-Dist: Adafruit-Blinka
Provides-Extra: optional
Requires-Dist: adafruit-circuitpython-display-text; extra == "optional"
Dynamic: license-file
